Workbook

Sheet Costs
A1: New Company Costs
A2: How to use: fill the yellow columns (A to H, J, K). Total (I) is calculated. Status: Actual = already spent, Possible = estimated or planned. Monthly and Yearly costs are totals per period; the Summary sheet converts them.
A4: Date | B4: Idea | C4: Category | D4: Item / description | E4: Cost type | F4: Status | G4: Unit cost (US$) | H4: Quantity | I4: Total (US$) | J4: Supplier | K4: Notes
A5: 46290 | B5: Idea 1 | C5: Legal & registration | D5: Company registration (example row, replace) | E5: One-time | F5: Possible | G5: 1500 | H5: 1 | I5: =IF(G5="","",G5*IF(H5="",1,H5)) | J5: Accountant | K5: Example: delete or overwrite
A6: 46290 | B6: Idea 1 | C6: Software & subscriptions | D6: Accounting software (example) | E6: Monthly | F6: Possible | G6: 120 | H6: 1 | I6: =IF(G6="","",G6*IF(H6="",1,H6)) | K6: Example
I7: =IF(G7="","",G7*IF(H7="",1,H7))
I8: =IF(G8="","",G8*IF(H8="",1,H8))
I9: =IF(G9="","",G9*IF(H9="",1,H9))
I10: =IF(G10="","",G10*IF(H10="",1,H10))
I11: =IF(G11="","",G11*IF(H11="",1,H11))
I12: =IF(G12="","",G12*IF(H12="",1,H12))
I13: =IF(G13="","",G13*IF(H13="",1,H13))
I14: =IF(G14="","",G14*IF(H14="",1,H14))
I15: =IF(G15="","",G15*IF(H15="",1,H15))
I16: =IF(G16="","",G16*IF(H16="",1,H16))
I17: =IF(G17="","",G17*IF(H17="",1,H17))
I18: =IF(G18="","",G18*IF(H18="",1,H18))
... I504: =IF(G504="","",G504*IF(H504="",1,H504))

Sheet Summary
A1: Summary
A2: All figures are formulas reading the Costs sheet. Monthly equivalent: Monthly as is, Yearly divided by 12. Set the planning horizon in B4.
A4: Planning horizon (months) | B4: 12 | C4: Assumption: edit to change how many months of running costs count toward the total.
A6: By idea (type idea names in column A, exactly as used in Costs)
A7: Idea | B7: One-time actual (US$) | C7: One-time possible (US$) | D7: Monthly actual (US$) | E7: Monthly possible (US$) | F7: Total actual (horizon) (US$) | G7: Total possible (horizon) (US$) | H7: Grand total (horizon) (US$)
A8: Idea 1 | B8: =IF($A8="",0,SUMIFS(Costs!$I$5:$I$504,Costs!$B$5:$B$504,$A8,Costs!$F$5:$F$504,"Actual",Costs!$E$5:$E$504,"One-time")) | C8: =IF($A8="",0,SUMIFS(Costs!$I$5:$I$504,Costs!$B$5:$B$504,$A8,Costs!$F$5:$F$504,"Possible",Costs!$E$5:$E$504,"One-time")) | D8: =IF($A8="",0,SUMIFS(Costs!$I$5:$I$504,Costs!$B$5:$B$504,$A8,Costs!$F$5:$F$504,"Actual",Costs!$E$5:$E$504,"Monthly")+SUMIFS(Costs!$I$5:$I$504,Costs!$B$5:$B$504,$A8,Costs!$F$5:$F$504,"Actual",Costs!$E$5:$E$504,"Yearly")/12) | E8: =IF($A8="",0,SUMIFS(Costs!$I$5:$I$504,Costs!$B$5:$B$504,$A8,Costs!$F$5:$F$504,"Possible",Costs!$E$5:$E$504,"Monthly")+SUMIFS(Costs!$I$5:$I$504,Costs!$B$5:$B$504,$A8,Costs!$F$5:$F$504,"Possible",Costs!$E$5:$E$504,"Yearly")/12) | F8: =B8+D8*$B$4 | G8: =C8+E8*$B$4 | H8: =F8+G8
B9: =IF($A9="",0,SUMIFS(Costs!$I$5:$I$504,Costs!$B$5:$B$504,$A9,Costs!$F$5:$F$504,"Actual",Costs!$E$5:$E$504,"One-time")) | C9: =IF($A9="",0,SUMIFS(Costs!$I$5:$I$504,Costs!$B$5:$B$504,$A9,Costs!$F$5:$F$504,"Possible",Costs!$E$5:$E$504,"One-time")) | D9: =IF($A9="",0,SUMIFS(Costs!$I$5:$I$504,Costs!$B$5:$B$504,$A9,Costs!$F$5:$F$504,"Actual",Costs!$E$5:$E$504,"Monthly")+SUMIFS(Costs!$I$5:$I$504,Costs!$B$5:$B$504,$A9,Costs!$F$5:$F$504,"Actual",Costs!$E$5:$E$504,"Yearly")/12) | E9: =IF($A9="",0,SUMIFS(Costs!$I$5:$I$504,Costs!$B$5:$B$504,$A9,Costs!$F$5:$F$504,"Possible",Costs!$E$5:$E$504,"Monthly")+SUMIFS(Costs!$I$5:$I$504,Costs!$B$5:$B$504,$A9,Costs!$F$5:$F$504,"Possible",Costs!$E$5:$E$504,"Yearly")/12) | F9: =B9+D9*$B$4 | G9: =C9+E9*$B$4 | H9: =F9+G9
B10: =IF($A10="",0,SUMIFS(Costs!$I$5:$I$504,Costs!$B$5:$B$504,$A10,Costs!$F$5:$F$504,"Actual",Costs!$E$5:$E$504,"One-time")) | C10: =IF($A10="",0,SUMIFS(Costs!$I$5:$I$504,Costs!$B$5:$B$504,$A10,Costs!$F$5:$F$504,"Possible",Costs!$E$5:$E$504,"One-time")) | D10: =IF($A10="",0,SUMIFS(Costs!$I$5:$I$504,Costs!$B$5:$B$504,$A10,Costs!$F$5:$F$504,"Actual",Costs!$E$5:$E$504,"Monthly")+SUMIFS(Costs!$I$5:$I$504,Costs!$B$5:$B$504,$A10,Costs!$F$5:$F$504,"Actual",Costs!$E$5:$E$504,"Yearly")/12) | E10: =IF($A10="",0,SUMIFS(Costs!$I$5:$I$504,Costs!$B$5:$B$504,$A10,Costs!$F$5:$F$504,"Possible",Costs!$E$5:$E$504,"Monthly")+SUMIFS(Costs!$I$5:$I$504,Costs!$B$5:$B$504,$A10,Costs!$F$5:$F$504,"Possible",Costs!$E$5:$E$504,"Yearly")/12) | F10: =B10+D10*$B$4 | G10: =C10+E10*$B$4 | H10: =F10+G10
B11: =IF($A11="",0,SUMIFS(Costs!$I$5:$I$504,Costs!$B$5:$B$504,$A11,Costs!$F$5:$F$504,"Actual",Costs!$E$5:$E$504,"One-time")) | C11: =IF($A11="",0,SUMIFS(Costs!$I$5:$I$504,Costs!$B$5:$B$504,$A11,Costs!$F$5:$F$504,"Possible",Costs!$E$5:$E$504,"One-time")) | D11: =IF($A11="",0,SUMIFS(Costs!$I$5:$I$504,Costs!$B$5:$B$504,$A11,Costs!$F$5:$F$504,"Actual",Costs!$E$5:$E$504,"Monthly")+SUMIFS(Costs!$I$5:$I$504,Costs!$B$5:$B$504,$A11,Costs!$F$5:$F$504,"Actual",Costs!$E$5:$E$504,"Yearly")/12) | E11: =IF($A11="",0,SUMIFS(Costs!$I$5:$I$504,Costs!$B$5:$B$504,$A11,Costs!$F$5:$F$504,"Possible",Costs!$E$5:$E$504,"Monthly")+SUMIFS(Costs!$I$5:$I$504,Costs!$B$5:$B$504,$A11,Costs!$F$5:$F$504,"Possible",Costs!$E$5:$E$504,"Yearly")/12) | F11: =B11+D11*$B$4 | G11: =C11+E11*$B$4 | H11: =F11+G11
B12: =IF($A12="",0,SUMIFS(Costs!$I$5:$I$504,Costs!$B$5:$B$504,$A12,Costs!$F$5:$F$504,"Actual",Costs!$E$5:$E$504,"One-time")) | C12: =IF($A12="",0,SUMIFS(Costs!$I$5:$I$504,Costs!$B$5:$B$504,$A12,Costs!$F$5:$F$504,"Possible",Costs!$E$5:$E$504,"One-time")) | D12: =IF($A12="",0,SUMIFS(Costs!$I$5:$I$504,Costs!$B$5:$B$504,$A12,Costs!$F$5:$F$504,"Actual",Costs!$E$5:$E$504,"Monthly")+SUMIFS(Costs!$I$5:$I$504,Costs!$B$5:$B$504,$A12,Costs!$F$5:$F$504,"Actual",Costs!$E$5:$E$504,"Yearly")/12) | E12: =IF($A12="",0,SUMIFS(Costs!$I$5:$I$504,Costs!$B$5:$B$504,$A12,Costs!$F$5:$F$504,"Possible",Costs!$E$5:$E$504,"Monthly")+SUMIFS(Costs!$I$5:$I$504,Costs!$B$5:$B$504,$A12,Costs!$F$5:$F$504,"Possible",Costs!$E$5:$E$504,"Yearly")/12) | F12: =B12+D12*$B$4 | G12: =C12+E12*$B$4 | H12: =F12+G12
B13: =IF($A13="",0,SUMIFS(Costs!$I$5:$I$504,Costs!$B$5:$B$504,$A13,Costs!$F$5:$F$504,"Actual",Costs!$E$5:$E$504,"One-time")) | C13: =IF($A13="",0,SUMIFS(Costs!$I$5:$I$504,Costs!$B$5:$B$504,$A13,Costs!$F$5:$F$504,"Possible",Costs!$E$5:$E$504,"One-time")) | D13: =IF($A13="",0,SUMIFS(Costs!$I$5:$I$504,Costs!$B$5:$B$504,$A13,Costs!$F$5:$F$504,"Actual",Costs!$E$5:$E$504,"Monthly")+SUMIFS(Costs!$I$5:$I$504,Costs!$B$5:$B$504,$A13,Costs!$F$5:$F$504,"Actual",Costs!$E$5:$E$504,"Yearly")/12) | E13: =IF($A13="",0,SUMIFS(Costs!$I$5:$I$504,Costs!$B$5:$B$504,$A13,Costs!$F$5:$F$504,"Possible",Costs!$E$5:$E$504,"Monthly")+SUMIFS(Costs!$I$5:$I$504,Costs!$B$5:$B$504,$A13,Costs!$F$5:$F$504,"Possible",Costs!$E$5:$E$504,"Yearly")/12) | F13: =B13+D13*$B$4 | G13: =C13+E13*$B$4 | H13: =F13+G13
B14: =IF($A14="",0,SUMIFS(Costs!$I$5:$I$504,Costs!$B$5:$B$504,$A14,Costs!$F$5:$F$504,"Actual",Costs!$E$5:$E$504,"One-time")) | C14: =IF($A14="",0,SUMIFS(Costs!$I$5:$I$504,Costs!$B$5:$B$504,$A14,Costs!$F$5:$F$504,"Possible",Costs!$E$5:$E$504,"One-time")) | D14: =IF($A14="",0,SUMIFS(Costs!$I$5:$I$504,Costs!$B$5:$B$504,$A14,Costs!$F$5:$F$504,"Actual",Costs!$E$5:$E$504,"Monthly")+SUMIFS(Costs!$I$5:$I$504,Costs!$B$5:$B$504,$A14,Costs!$F$5:$F$504,"Actual",Costs!$E$5:$E$504,"Yearly")/12) | E14: =IF($A14="",0,SUMIFS(Costs!$I$5:$I$504,Costs!$B$5:$B$504,$A14,Costs!$F$5:$F$504,"Possible",Costs!$E$5:$E$504,"Monthly")+SUMIFS(Costs!$I$5:$I$504,Costs!$B$5:$B$504,$A14,Costs!$F$5:$F$504,"Possible",Costs!$E$5:$E$504,"Yearly")/12) | F14: =B14+D14*$B$4 | G14: =C14+E14*$B$4 | H14: =F14+G14
B15: =IF($A15="",0,SUMIFS(Costs!$I$5:$I$504,Costs!$B$5:$B$504,$A15,Costs!$F$5:$F$504,"Actual",Costs!$E$5:$E$504,"One-time")) | C15: =IF($A15="",0,SUMIFS(Costs!$I$5:$I$504,Costs!$B$5:$B$504,$A15,Costs!$F$5:$F$504,"Possible",Costs!$E$5:$E$504,"One-time")) | D15: =IF($A15="",0,SUMIFS(Costs!$I$5:$I$504,Costs!$B$5:$B$504,$A15,Costs!$F$5:$F$504,"Actual",Costs!$E$5:$E$504,"Monthly")+SUMIFS(Costs!$I$5:$I$504,Costs!$B$5:$B$504,$A15,Costs!$F$5:$F$504,"Actual",Costs!$E$5:$E$504,"Yearly")/12) | E15: =IF($A15="",0,SUMIFS(Costs!$I$5:$I$504,Costs!$B$5:$B$504,$A15,Costs!$F$5:$F$504,"Possible",Costs!$E$5:$E$504,"Monthly")+SUMIFS(Costs!$I$5:$I$504,Costs!$B$5:$B$504,$A15,Costs!$F$5:$F$504,"Possible",Costs!$E$5:$E$504,"Yearly")/12) | F15: =B15+D15*$B$4 | G15: =C15+E15*$B$4 | H15: =F15+G15
B16: =IF($A16="",0,SUMIFS(Costs!$I$5:$I$504,Costs!$B$5:$B$504,$A16,Costs!$F$5:$F$504,"Actual",Costs!$E$5:$E$504,"One-time")) | C16: =IF($A16="",0,SUMIFS(Costs!$I$5:$I$504,Costs!$B$5:$B$504,$A16,Costs!$F$5:$F$504,"Possible",Costs!$E$5:$E$504,"One-time")) | D16: =IF($A16="",0,SUMIFS(Costs!$I$5:$I$504,Costs!$B$5:$B$504,$A16,Costs!$F$5:$F$504,"Actual",Costs!$E$5:$E$504,"Monthly")+SUMIFS(Costs!$I$5:$I$504,Costs!$B$5:$B$504,$A16,Costs!$F$5:$F$504,"Actual",Costs!$E$5:$E$504,"Yearly")/12) | E16: =IF($A16="",0,SUMIFS(Costs!$I$5:$I$504,Costs!$B$5:$B$504,$A16,Costs!$F$5:$F$504,"Possible",Costs!$E$5:$E$504,"Monthly")+SUMIFS(Costs!$I$5:$I$504,Costs!$B$5:$B$504,$A16,Costs!$F$5:$F$504,"Possible",Costs!$E$5:$E$504,"Yearly")/12) | F16: =B16+D16*$B$4 | G16: =C16+E16*$B$4 | H16: =F16+G16
B17: =IF($A17="",0,SUMIFS(Costs!$I$5:$I$504,Costs!$B$5:$B$504,$A17,Costs!$F$5:$F$504,"Actual",Costs!$E$5:$E$504,"One-time")) | C17: =IF($A17="",0,SUMIFS(Costs!$I$5:$I$504,Costs!$B$5:$B$504,$A17,Costs!$F$5:$F$504,"Possible",Costs!$E$5:$E$504,"One-time")) | D17: =IF($A17="",0,SUMIFS(Costs!$I$5:$I$504,Costs!$B$5:$B$504,$A17,Costs!$F$5:$F$504,"Actual",Costs!$E$5:$E$504,"Monthly")+SUMIFS(Costs!$I$5:$I$504,Costs!$B$5:$B$504,$A17,Costs!$F$5:$F$504,"Actual",Costs!$E$5:$E$504,"Yearly")/12) | E17: =IF($A17="",0,SUMIFS(Costs!$I$5:$I$504,Costs!$B$5:$B$504,$A17,Costs!$F$5:$F$504,"Possible",Costs!$E$5:$E$504,"Monthly")+SUMIFS(Costs!$I$5:$I$504,Costs!$B$5:$B$504,$A17,Costs!$F$5:$F$504,"Possible",Costs!$E$5:$E$504,"Yearly")/12) | F17: =B17+D17*$B$4 | G17: =C17+E17*$B$4 | H17: =F17+G17
A18: Total | B18: =SUM(B8:B17) | C18: =SUM(C8:C17) | D18: =SUM(D8:D17) | E18: =SUM(E8:E17) | F18: =SUM(F8:F17) | G18: =SUM(G8:G17) | H18: =SUM(H8:H17)
A21: By category
A22: Category | B22: One-time actual (US$) | C22: One-time possible (US$) | D22: Monthly actual (US$) | E22: Monthly possible (US$) | F22: Total actual (horizon) (US$) | G22: Total possible (horizon) (US$) | H22: Grand total (horizon) (US$)
A23: =Lists!A2 | B23: =IF($A23="",0,SUMIFS(Costs!$I$5:$I$504,Costs!$C$5:$C$504,$A23,Costs!$F$5:$F$504,"Actual",Costs!$E$5:$E$504,"One-time")) | C23: =IF($A23="",0,SUMIFS(Costs!$I$5:$I$504,Costs!$C$5:$C$504,$A23,Costs!$F$5:$F$504,"Possible",Costs!$E$5:$E$504,"One-time")) | D23: =IF($A23="",0,SUMIFS(Costs!$I$5:$I$504,Costs!$C$5:$C$504,$A23,Costs!$F$5:$F$504,"Actual",Costs!$E$5:$E$504,"Monthly")+SUMIFS(Costs!$I$5:$I$504,Costs!$C$5:$C$504,$A23,Costs!$F$5:$F$504,"Actual",Costs!$E$5:$E$504,"Yearly")/12) | E23: =IF($A23="",0,SUMIFS(Costs!$I$5:$I$504,Costs!$C$5:$C$504,$A23,Costs!$F$5:$F$504,"Possible",Costs!$E$5:$E$504,"Monthly")+SUMIFS(Costs!$I$5:$I$504,Costs!$C$5:$C$504,$A23,Costs!$F$5:$F$504,"Possible",Costs!$E$5:$E$504,"Yearly")/12) | F23: =B23+D23*$B$4 | G23: =C23+E23*$B$4 | H23: =F23+G23
A24: =Lists!A3 | B24: =IF($A24="",0,SUMIFS(Costs!$I$5:$I$504,Costs!$C$5:$C$504,$A24,Costs!$F$5:$F$504,"Actual",Costs!$E$5:$E$504,"One-time")) | C24: =IF($A24="",0,SUMIFS(Costs!$I$5:$I$504,Costs!$C$5:$C$504,$A24,Costs!$F$5:$F$504,"Possible",Costs!$E$5:$E$504,"One-time")) | D24: =IF($A24="",0,SUMIFS(Costs!$I$5:$I$504,Costs!$C$5:$C$504,$A24,Costs!$F$5:$F$504,"Actual",Costs!$E$5:$E$504,"Monthly")+SUMIFS(Costs!$I$5:$I$504,Costs!$C$5:$C$504,$A24,Costs!$F$5:$F$504,"Actual",Costs!$E$5:$E$504,"Yearly")/12) | E24: =IF($A24="",0,SUMIFS(Costs!$I$5:$I$504,Costs!$C$5:$C$504,$A24,Costs!$F$5:$F$504,"Possible",Costs!$E$5:$E$504,"Monthly")+SUMIFS(Costs!$I$5:$I$504,Costs!$C$5:$C$504,$A24,Costs!$F$5:$F$504,"Possible",Costs!$E$5:$E$504,"Yearly")/12) | F24: =B24+D24*$B$4 | G24: =C24+E24*$B$4 | H24: =F24+G24
A25: =Lists!A4 | B25: =IF($A25="",0,SUMIFS(Costs!$I$5:$I$504,Costs!$C$5:$C$504,$A25,Costs!$F$5:$F$504,"Actual",Costs!$E$5:$E$504,"One-time")) | C25: =IF($A25="",0,SUMIFS(Costs!$I$5:$I$504,Costs!$C$5:$C$504,$A25,Costs!$F$5:$F$504,"Possible",Costs!$E$5:$E$504,"One-time")) | D25: =IF($A25="",0,SUMIFS(Costs!$I$5:$I$504,Costs!$C$5:$C$504,$A25,Costs!$F$5:$F$504,"Actual",Costs!$E$5:$E$504,"Monthly")+SUMIFS(Costs!$I$5:$I$504,Costs!$C$5:$C$504,$A25,Costs!$F$5:$F$504,"Actual",Costs!$E$5:$E$504,"Yearly")/12) | E25: =IF($A25="",0,SUMIFS(Costs!$I$5:$I$504,Costs!$C$5:$C$504,$A25,Costs!$F$5:$F$504,"Possible",Costs!$E$5:$E$504,"Monthly")+SUMIFS(Costs!$I$5:$I$504,Costs!$C$5:$C$504,$A25,Costs!$F$5:$F$504,"Possible",Costs!$E$5:$E$504,"Yearly")/12) | F25: =B25+D25*$B$4 | G25: =C25+E25*$B$4 | H25: =F25+G25
A26: =Lists!A5 | B26: =IF($A26="",0,SUMIFS(Costs!$I$5:$I$504,Costs!$C$5:$C$504,$A26,Costs!$F$5:$F$504,"Actual",Costs!$E$5:$E$504,"One-time")) | C26: =IF($A26="",0,SUMIFS(Costs!$I$5:$I$504,Costs!$C$5:$C$504,$A26,Costs!$F$5:$F$504,"Possible",Costs!$E$5:$E$504,"One-time")) | D26: =IF($A26="",0,SUMIFS(Costs!$I$5:$I$504,Costs!$C$5:$C$504,$A26,Costs!$F$5:$F$504,"Actual",Costs!$E$5:$E$504,"Monthly")+SUMIFS(Costs!$I$5:$I$504,Costs!$C$5:$C$504,$A26,Costs!$F$5:$F$504,"Actual",Costs!$E$5:$E$504,"Yearly")/12) | E26: =IF($A26="",0,SUMIFS(Costs!$I$5:$I$504,Costs!$C$5:$C$504,$A26,Costs!$F$5:$F$504,"Possible",Costs!$E$5:$E$504,"Monthly")+SUMIFS(Costs!$I$5:$I$504,Costs!$C$5:$C$504,$A26,Costs!$F$5:$F$504,"Possible",Costs!$E$5:$E$504,"Yearly")/12) | F26: =B26+D26*$B$4 | G26: =C26+E26*$B$4 | H26: =F26+G26
A27: =Lists!A6 | B27: =IF($A27="",0,SUMIFS(Costs!$I$5:$I$504,Costs!$C$5:$C$504,$A27,Costs!$F$5:$F$504,"Actual",Costs!$E$5:$E$504,"One-time")) | C27: =IF($A27="",0,SUMIFS(Costs!$I$5:$I$504,Costs!$C$5:$C$504,$A27,Costs!$F$5:$F$504,"Possible",Costs!$E$5:$E$504,"One-time")) | D27: =IF($A27="",0,SUMIFS(Costs!$I$5:$I$504,Costs!$C$5:$C$504,$A27,Costs!$F$5:$F$504,"Actual",Costs!$E$5:$E$504,"Monthly")+SUMIFS(Costs!$I$5:$I$504,Costs!$C$5:$C$504,$A27,Costs!$F$5:$F$504,"Actual",Costs!$E$5:$E$504,"Yearly")/12) | E27: =IF($A27="",0,SUMIFS(Costs!$I$5:$I$504,Costs!$C$5:$C$504,$A27,Costs!$F$5:$F$504,"Possible",Costs!$E$5:$E$504,"Monthly")+SUMIFS(Costs!$I$5:$I$504,Costs!$C$5:$C$504,$A27,Costs!$F$5:$F$504,"Possible",Costs!$E$5:$E$504,"Yearly")/12) | F27: =B27+D27*$B$4 | G27: =C27+E27*$B$4 | H27: =F27+G27
A28: =Lists!A7 | B28: =IF($A28="",0,SUMIFS(Costs!$I$5:$I$504,Costs!$C$5:$C$504,$A28,Costs!$F$5:$F$504,"Actual",Costs!$E$5:$E$504,"One-time")) | C28: =IF($A28="",0,SUMIFS(Costs!$I$5:$I$504,Costs!$C$5:$C$504,$A28,Costs!$F$5:$F$504,"Possible",Costs!$E$5:$E$504,"One-time")) | D28: =IF($A28="",0,SUMIFS(Costs!$I$5:$I$504,Costs!$C$5:$C$504,$A28,Costs!$F$5:$F$504,"Actual",Costs!$E$5:$E$504,"Monthly")+SUMIFS(Costs!$I$5:$I$504,Costs!$C$5:$C$504,$A28,Costs!$F$5:$F$504,"Actual",Costs!$E$5:$E$504,"Yearly")/12) | E28: =IF($A28="",0,SUMIFS(Costs!$I$5:$I$504,Costs!$C$5:$C$504,$A28,Costs!$F$5:$F$504,"Possible",Costs!$E$5:$E$504,"Monthly")+SUMIFS(Costs!$I$5:$I$504,Costs!$C$5:$C$504,$A28,Costs!$F$5:$F$504,"Possible",Costs!$E$5:$E$504,"Yearly")/12) | F28: =B28+D28*$B$4 | G28: =C28+E28*$B$4 | H28: =F28+G28
A29: =Lists!A8 | B29: =IF($A29="",0,SUMIFS(Costs!$I$5:$I$504,Costs!$C$5:$C$504,$A29,Costs!$F$5:$F$504,"Actual",Costs!$E$5:$E$504,"One-time")) | C29: =IF($A29="",0,SUMIFS(Costs!$I$5:$I$504,Costs!$C$5:$C$504,$A29,Costs!$F$5:$F$504,"Possible",Costs!$E$5:$E$504,"One-time")) | D29: =IF($A29="",0,SUMIFS(Costs!$I$5:$I$504,Costs!$C$5:$C$504,$A29,Costs!$F$5:$F$504,"Actual",Costs!$E$5:$E$504,"Monthly")+SUMIFS(Costs!$I$5:$I$504,Costs!$C$5:$C$504,$A29,Costs!$F$5:$F$504,"Actual",Costs!$E$5:$E$504,"Yearly")/12) | E29: =IF($A29="",0,SUMIFS(Costs!$I$5:$I$504,Costs!$C$5:$C$504,$A29,Costs!$F$5:$F$504,"Possible",Costs!$E$5:$E$504,"Monthly")+SUMIFS(Costs!$I$5:$I$504,Costs!$C$5:$C$504,$A29,Costs!$F$5:$F$504,"Possible",Costs!$E$5:$E$504,"Yearly")/12) | F29: =B29+D29*$B$4 | G29: =C29+E29*$B$4 | H29: =F29+G29
A30: =Lists!A9 | B30: =IF($A30="",0,SUMIFS(Costs!$I$5:$I$504,Costs!$C$5:$C$504,$A30,Costs!$F$5:$F$504,"Actual",Costs!$E$5:$E$504,"One-time")) | C30: =IF($A30="",0,SUMIFS(Costs!$I$5:$I$504,Costs!$C$5:$C$504,$A30,Costs!$F$5:$F$504,"Possible",Costs!$E$5:$E$504,"One-time")) | D30: =IF($A30="",0,SUMIFS(Costs!$I$5:$I$504,Costs!$C$5:$C$504,$A30,Costs!$F$5:$F$504,"Actual",Costs!$E$5:$E$504,"Monthly")+SUMIFS(Costs!$I$5:$I$504,Costs!$C$5:$C$504,$A30,Costs!$F$5:$F$504,"Actual",Costs!$E$5:$E$504,"Yearly")/12) | E30: =IF($A30="",0,SUMIFS(Costs!$I$5:$I$504,Costs!$C$5:$C$504,$A30,Costs!$F$5:$F$504,"Possible",Costs!$E$5:$E$504,"Monthly")+SUMIFS(Costs!$I$5:$I$504,Costs!$C$5:$C$504,$A30,Costs!$F$5:$F$504,"Possible",Costs!$E$5:$E$504,"Yearly")/12) | F30: =B30+D30*$B$4 | G30: =C30+E30*$B$4 | H30: =F30+G30
A31: =Lists!A10 | B31: =IF($A31="",0,SUMIFS(Costs!$I$5:$I$504,Costs!$C$5:$C$504,$A31,Costs!$F$5:$F$504,"Actual",Costs!$E$5:$E$504,"One-time")) | C31: =IF($A31="",0,SUMIFS(Costs!$I$5:$I$504,Costs!$C$5:$C$504,$A31,Costs!$F$5:$F$504,"Possible",Costs!$E$5:$E$504,"One-time")) | D31: =IF($A31="",0,SUMIFS(Costs!$I$5:$I$504,Costs!$C$5:$C$504,$A31,Costs!$F$5:$F$504,"Actual",Costs!$E$5:$E$504,"Monthly")+SUMIFS(Costs!$I$5:$I$504,Costs!$C$5:$C$504,$A31,Costs!$F$5:$F$504,"Actual",Costs!$E$5:$E$504,"Yearly")/12) | E31: =IF($A31="",0,SUMIFS(Costs!$I$5:$I$504,Costs!$C$5:$C$504,$A31,Costs!$F$5:$F$504,"Possible",Costs!$E$5:$E$504,"Monthly")+SUMIFS(Costs!$I$5:$I$504,Costs!$C$5:$C$504,$A31,Costs!$F$5:$F$504,"Possible",Costs!$E$5:$E$504,"Yearly")/12) | F31: =B31+D31*$B$4 | G31: =C31+E31*$B$4 | H31: =F31+G31
A32: =Lists!A11 | B32: =IF($A32="",0,SUMIFS(Costs!$I$5:$I$504,Costs!$C$5:$C$504,$A32,Costs!$F$5:$F$504,"Actual",Costs!$E$5:$E$504,"One-time")) | C32: =IF($A32="",0,SUMIFS(Costs!$I$5:$I$504,Costs!$C$5:$C$504,$A32,Costs!$F$5:$F$504,"Possible",Costs!$E$5:$E$504,"One-time")) | D32: =IF($A32="",0,SUMIFS(Costs!$I$5:$I$504,Costs!$C$5:$C$504,$A32,Costs!$F$5:$F$504,"Actual",Costs!$E$5:$E$504,"Monthly")+SUMIFS(Costs!$I$5:$I$504,Costs!$C$5:$C$504,$A32,Costs!$F$5:$F$504,"Actual",Costs!$E$5:$E$504,"Yearly")/12) | E32: =IF($A32="",0,SUMIFS(Costs!$I$5:$I$504,Costs!$C$5:$C$504,$A32,Costs!$F$5:$F$504,"Possible",Costs!$E$5:$E$504,"Monthly")+SUMIFS(Costs!$I$5:$I$504,Costs!$C$5:$C$504,$A32,Costs!$F$5:$F$504,"Possible",Costs!$E$5:$E$504,"Yearly")/12) | F32: =B32+D32*$B$4 | G32: =C32+E32*$B$4 | H32: =F32+G32
A33: =Lists!A12 | B33: =IF($A33="",0,SUMIFS(Costs!$I$5:$I$504,Costs!$C$5:$C$504,$A33,Costs!$F$5:$F$504,"Actual",Costs!$E$5:$E$504,"One-time")) | C33: =IF($A33="",0,SUMIFS(Costs!$I$5:$I$504,Costs!$C$5:$C$504,$A33,Costs!$F$5:$F$504,"Possible",Costs!$E$5:$E$504,"One-time")) | D33: =IF($A33="",0,SUMIFS(Costs!$I$5:$I$504,Costs!$C$5:$C$504,$A33,Costs!$F$5:$F$504,"Actual",Costs!$E$5:$E$504,"Monthly")+SUMIFS(Costs!$I$5:$I$504,Costs!$C$5:$C$504,$A33,Costs!$F$5:$F$504,"Actual",Costs!$E$5:$E$504,"Yearly")/12) | E33: =IF($A33="",0,SUMIFS(Costs!$I$5:$I$504,Costs!$C$5:$C$504,$A33,Costs!$F$5:$F$504,"Possible",Costs!$E$5:$E$504,"Monthly")+SUMIFS(Costs!$I$5:$I$504,Costs!$C$5:$C$504,$A33,Costs!$F$5:$F$504,"Possible",Costs!$E$5:$E$504,"Yearly")/12) | F33: =B33+D33*$B$4 | G33: =C33+E33*$B$4 | H33: =F33+G33
A34: =Lists!A13 | B34: =IF($A34="",0,SUMIFS(Costs!$I$5:$I$504,Costs!$C$5:$C$504,$A34,Costs!$F$5:$F$504,"Actual",Costs!$E$5:$E$504,"One-time")) | C34: =IF($A34="",0,SUMIFS(Costs!$I$5:$I$504,Costs!$C$5:$C$504,$A34,Costs!$F$5:$F$504,"Possible",Costs!$E$5:$E$504,"One-time")) | D34: =IF($A34="",0,SUMIFS(Costs!$I$5:$I$504,Costs!$C$5:$C$504,$A34,Costs!$F$5:$F$504,"Actual",Costs!$E$5:$E$504,"Monthly")+SUMIFS(Costs!$I$5:$I$504,Costs!$C$5:$C$504,$A34,Costs!$F$5:$F$504,"Actual",Costs!$E$5:$E$504,"Yearly")/12) | E34: =IF($A34="",0,SUMIFS(Costs!$I$5:$I$504,Costs!$C$5:$C$504,$A34,Costs!$F$5:$F$504,"Possible",Costs!$E$5:$E$504,"Monthly")+SUMIFS(Costs!$I$5:$I$504,Costs!$C$5:$C$504,$A34,Costs!$F$5:$F$504,"Possible",Costs!$E$5:$E$504,"Yearly")/12) | F34: =B34+D34*$B$4 | G34: =C34+E34*$B$4 | H34: =F34+G34
... A36: =Lists!A15 | B36: =IF($A36="",0,SUMIFS(Costs!$I$5:$I$504,Costs!$C$5:$C$504,$A36,Costs!$F$5:$F$504,"Actual",Costs!$E$5:$E$504,"One-time")) | C36: =IF($A36="",0,SUMIFS(Costs!$I$5:$I$504,Costs!$C$5:$C$504,$A36,Costs!$F$5:$F$504,"Possible",Costs!$E$5:$E$504,"One-time")) | D36: =IF($A36="",0,SUMIFS(Costs!$I$5:$I$504,Costs!$C$5:$C$504,$A36,Costs!$F$5:$F$504,"Actual",Costs!$E$5:$E$504,"Monthly")+SUMIFS(Costs!$I$5:$I$504,Costs!$C$5:$C$504,$A36,Costs!$F$5:$F$504,"Actual",Costs!$E$5:$E$504,"Yearly")/12) | E36: =IF($A36="",0,SUMIFS(Costs!$I$5:$I$504,Costs!$C$5:$C$504,$A36,Costs!$F$5:$F$504,"Possible",Costs!$E$5:$E$504,"Monthly")+SUMIFS(Costs!$I$5:$I$504,Costs!$C$5:$C$504,$A36,Costs!$F$5:$F$504,"Possible",Costs!$E$5:$E$504,"Yearly")/12) | F36: =B36+D36*$B$4 | G36: =C36+E36*$B$4 | H36: =F36+G36
A37: Total | B37: =SUM(B23:B36) | C37: =SUM(C23:C36) | D37: =SUM(D23:D36) | E37: =SUM(E23:E36) | F37: =SUM(F23:F36) | G37: =SUM(G23:G36) | H37: =SUM(H23:H36)

Sheet Lists
A1: Categories | B1: Cost type | C1: Status | E1: Edit column A (blue) to change the category dropdown. Up to row 40 is read.
A2: Legal & registration | B2: One-time | C2: Actual
A3: Accounting & taxes | B3: Monthly | C3: Possible
A4: Rent & office | B4: Yearly
A5: Equipment
A6: Software & subscriptions
A7: Website & domain
A8: Marketing
A9: Salaries & freelancers
A10: Inventory & materials
A11: Utilities
A12: Insurance
A13: Travel
A14: Training
A15: Other
